{
  "description": "A full-width call-to-action banner with bold heading, supporting text, and prominent button. Designed to capture attention and drive conversions. Use between content sections for sign-ups, downloads, or contact. Layout: colored background with centered heading, description, and large contrasting button. Optional background image with overlay.",
  "fields": [
    {
      "name": "heading",
      "required": true,
      "title": "Heading",
      "type": "string"
    },
    {
      "name": "description",
      "required": false,
      "title": "Description",
      "type": "textarea"
    },
    {
      "name": "background_image",
      "required": false,
      "title": "Background Image",
      "type": "image"
    },
    {
      "initialValue": "accent",
      "name": "style",
      "options": [
        "accent",
        "dark",
        "light"
      ],
      "title": "Style",
      "type": "select"
    },
    {
      "name": "button",
      "title": "Button",
      "type": "link"
    }
  ],
  "icon": "megaphone",
  "label": "CTA Banner",
  "slug": "cb-cta-banner",
  "test_data": {
    "background_image": "",
    "button": {
      "alt": "",
      "target": "",
      "text": "Start Free Trial",
      "url": "/signup"
    },
    "description": "Join thousands of creators who trust Squilla to power their websites. Start building something amazing today.",
    "heading": "Ready to Get Started?",
    "style": "accent"
  }
}
