{
  "name": "Contact",
  "description": "Contact page with editorial intro and a form rendered by the Forms extension",
  "thumbnail": "",
  "blocks": [
    {
      "type": "rich-text",
      "fields": {
        "eyebrow": "Contact",
        "heading": "Let's start a conversation.",
        "body": "<p>Have a question, a partnership idea, or just want to see if Squilla is right for your team? We read every message and respond within one business day.</p>"
      }
    },
    {
      "type": "vibe-form",
      "fields": {
        "form_slug": "contact",
        "heading": "Get in touch"
      }
    },
    {
      "type": "faq",
      "fields": {
        "heading": "Frequently Asked",
        "items": [
          {
            "question": "How do I create the contact form?",
            "answer": "<p>Visit <a href=\"/admin/forms\">Admin → Forms</a> and create a new form with slug <code>contact</code>. The block on this page will pick it up automatically.</p>"
          },
          {
            "question": "Can I migrate from another CMS?",
            "answer": "<p>Yes — Squilla can import content via the MCP server. See the docs for details.</p>"
          }
        ]
      }
    }
  ]
}
